tachyons/__init__.py
tachyons/__main__.py
tachyons/date.py
tachyons/dbtypes.py
tachyons/djproxy.py
tachyons/encryption.py
tachyons/forms.py
tachyons/main.py
tachyons/models.py
tachyons/path.py
tachyons/request.py
tachyons/response.py
tachyons/routing.py
tachyons/serializers.py
tachyons/settings.py
tachyons/databases/__init__.py
tachyons/databases/filebase.py
tachyons/databases/proxies/__init__.py
tachyons/databases/proxies/django.py
tachyons/docs/__init__.py
tachyons/exceptions/__init__.py
tachyons/exceptions/http.py
tachyons/integrations/__init__.py
tachyons/integrations/gmail.py
tachyons/integrations/aws/__init__.py
tachyons/integrations/aws/s3.py
tachyons/integrations/google/__init__.py
tachyons/integrations/google/drive.py
tachyons/io/__init__.py
tachyons/io/file_reader.py
tachyons/io/file_writer.py
tachyons/parsing/__init__.py
tachyons/parsing/base.py
tachyons/routers/__init__.py
tachyons/routers/base.py
tachyons/routers/django.py
tachyons/routers/fastapi.py
tachyons/routers/flask.py
tachyons/utils/__init__.py
tachyons/validators/__init__.py
tachyons/wrappers/__init__.py
tachyons/wrappers/django.py
tachyons/wrappers/fastapi.py
tachyons/wrappers/flask.py
tachyons-1.0.6.dist-info/licenses/LICENSE
tachyons-1.0.6.dist-info/METADATA
tachyons-1.0.6.dist-info/WHEEL
tachyons-1.0.6.dist-info/top_level.txt
tachyons-1.0.6.dist-info/RECORD
