Metadata-Version: 2.4
Name: tachyons
Version: 1.0.6
Summary: tachyons
Home-page: https://github.com/Abdelmathin/tachyons
Author: Abdelmathin Habachi
Author-email: contact@abdelmathin.com
Classifier: Programming Language :: Python :: 3
Classifier: License :: OSI Approved :: MIT License
Classifier: Operating System :: OS Independent
Requires-Python: >=3.7
License-File: LICENSE
Requires-Dist: requests
Dynamic: author
Dynamic: author-email
Dynamic: classifier
Dynamic: description
Dynamic: description-content-type
Dynamic: home-page
Dynamic: license-file
Dynamic: requires-dist
Dynamic: requires-python
Dynamic: summary
